{
  "maxAmount": 100,
  "defaultsByBiome": {
    "DEEP_FOREST": {
      "grass": [
        18,
        36
      ],
      "berries": [
        6,
        12
      ],
      "mushrooms": [
        8,
        19
      ],
      "herbs": [
        4,
        11
      ]
    },
    "FOREST": {
      "grass": [
        16,
        32
      ],
      "berries": [
        6,
        12
      ],
      "mushrooms": [
        8,
        19
      ],
      "herbs": [
        4,
        11
      ]
    },
    "CLEARING": {
      "grass": [
        28,
        56
      ],
      "berries": [
        1,
        4
      ],
      "herbs": [
        9,
        20
      ]
    },
    "RIVER": {
      "grass": [
        12,
        26
      ],
      "herbs": [
        6,
        12
      ]
    },
    "VILLAGE": {}
  },
  "locationOverrides": {
    "start_border_camp": {
      "grass": 0,
      "berries": 0,
      "mushrooms": 0,
      "herbs": 0
    },
    "start_border_watchtower": {
      "grass": 0,
      "berries": 0,
      "mushrooms": 0,
      "herbs": 0
    },
    "old_bridge_west_span": {
      "grass": 0,
      "berries": 0,
      "mushrooms": 0,
      "herbs": 0
    },
    "old_bridge_east_span": {
      "grass": 0,
      "berries": 0,
      "mushrooms": 0,
      "herbs": 0
    },
    "closed_east_gate": {
      "grass": 0,
      "berries": 0,
      "mushrooms": 0,
      "herbs": 0
    },
    "meadow_16_05": {
      "grass": 0,
      "berries": 0,
      "herbs": 0
    },
    "dream_tutorial_hub": {
      "grass": 0,
      "berries": 0,
      "mushrooms": 0,
      "herbs": 0
    },
    "dream_tutorial_foraging": {
      "grass": 0,
      "berries": 6,
      "mushrooms": 0,
      "herbs": 3
    },
    "dream_tutorial_rest": {
      "grass": 0,
      "berries": 0,
      "mushrooms": 0,
      "herbs": 0
    },
    "dream_tutorial_deep_rest": {
      "grass": 0,
      "berries": 0,
      "mushrooms": 0,
      "herbs": 0
    },
    "dream_tutorial_time": {
      "grass": 0,
      "berries": 0,
      "mushrooms": 0,
      "herbs": 0
    },
    "dream_tutorial_safety": {
      "grass": 0,
      "berries": 0,
      "mushrooms": 0,
      "herbs": 0
    },
    "dream_tutorial_observation": {
      "grass": 0,
      "berries": 0,
      "mushrooms": 0,
      "herbs": 0
    }
  },
  "notes": [
    "Resource nodes are generated deterministically from location biome and key.",
    "Grass is an ecology-only food layer for herbivores and is hidden from player gather menus.",
    "Forest and deep forest: grass, berries, mushrooms, herbs.",
    "Dry luka / CLEARING: grass, berries and herbs; no mushrooms.",
    "Riverbank / RIVER: grass and herbs only.",
    "Bridge spans, start camp and closed gate intentionally have no vegetation resources.",
    "meadow_16_05 starts exhausted for visible ecology testing.",
    "Dream tutorial locations opt out of biome-generated ecology resources except the explicit foraging lesson.",
    "Set a resource to 0 in locationOverrides to remove it from that location."
  ]
}
